funcnodes_weather/__init__.py
funcnodes_weather/weatherapi/__init__.py
funcnodes_weather-0.1.2.dist-info/entry_points.txt
funcnodes_weather-0.1.2.dist-info/LICENSE
funcnodes_weather-0.1.2.dist-info/METADATA
funcnodes_weather-0.1.2.dist-info/WHEEL
funcnodes_weather-0.1.2.dist-info/RECORD
