Metadata-Version: 2.1
Name: funcnodes-weather
Version: 0.1.2
Summary: 
License: AGPL-3.0
Author: Julian Kimmig
Author-email: julian.kimmig@gmx.net
Requires-Python: >=3.11
Classifier: License :: OSI Approved :: GNU Affero General Public License v3
Classifier: Programming Language :: Python :: 3
Classifier: Programming Language :: Python :: 3.11
Classifier: Programming Language :: Python :: 3.12
Classifier: Programming Language :: Python :: 3.13
Requires-Dist: funcnodes
Requires-Dist: funcnodes-pandas
Requires-Dist: funcnodes-plotly
Requires-Dist: geocoder
